{
  "roots": [
    {
      "key": "2ajryvqow43elplox2nvgt0",
      "title": "Hello Visitor",
      "icon": null,
      "hasTitleNumberOutlined": false,
      "vaultName": "vault",
      "children": [
        {
          "key": "cj841uoi4a89gvhzf6qss2u",
          "title": "Notes from the field",
          "icon": "plusOutlined",
          "hasTitleNumberOutlined": false,
          "vaultName": "vault",
          "children": [
            {
              "key": "suyvdgeyipdebxr61uoo1xd",
              "title": "csharp",
              "icon": null,
              "hasTitleNumberOutlined": false,
              "vaultName": "vault",
              "children": []
            },
            {
              "key": "ispyuxecejflrr2t0trxrmg",
              "title": "powershell",
              "icon": null,
              "hasTitleNumberOutlined": false,
              "vaultName": "vault",
              "children": []
            }
          ]
        },
        {
          "key": "kmodkqrr8soyq59b5twkopo",
          "title": "Recommendations",
          "icon": null,
          "hasTitleNumberOutlined": false,
          "vaultName": "vault",
          "children": []
        }
      ]
    }
  ],
  "child2parent": {
    "403": null,
    "2ajryvqow43elplox2nvgt0": null,
    "cj841uoi4a89gvhzf6qss2u": "2ajryvqow43elplox2nvgt0",
    "ispyuxecejflrr2t0trxrmg": "cj841uoi4a89gvhzf6qss2u",
    "suyvdgeyipdebxr61uoo1xd": "cj841uoi4a89gvhzf6qss2u",
    "kmodkqrr8soyq59b5twkopo": "2ajryvqow43elplox2nvgt0"
  }
}
